transx/__init__.py
transx/__version__.py
transx/api/__init__.py
transx/api/interpreter.py
transx/api/locale.py
transx/api/message.py
transx/api/mo.py
transx/api/po.py
transx/api/pot.py
transx/api/translate.py
transx/api/translation_catalog.py
transx/app.py
transx/cli.py
transx/constants.py
transx/context/__init__.py
transx/context/manager.py
transx/core.py
transx/exceptions.py
transx/extensions/__init__.py
transx/extensions/qt.py
transx/internal/__init__.py
transx/internal/compat.py
transx/internal/filesystem.py
transx/internal/logging.py
transx-0.6.1.dist-info/LICENSE
transx-0.6.1.dist-info/METADATA
transx-0.6.1.dist-info/WHEEL
transx-0.6.1.dist-info/entry_points.txt
transx-0.6.1.dist-info/RECORD
